my_knapsack_solver/Main.py
my_knapsack_solver/__init__.py
my_knapsack_solver-0.1.dist-info/METADATA
my_knapsack_solver-0.1.dist-info/WHEEL
my_knapsack_solver-0.1.dist-info/top_level.txt
my_knapsack_solver-0.1.dist-info/RECORD
