Metadata-Version: 2.1
Name: my-knapsack-solver
Version: 0.1
Summary: A simple 0/1 knapsack problem solver.
Author: Your Name
Author-email: your.email@example.com
Classifier: Programming Language :: Python :: 3
Classifier: License :: OSI Approved :: MIT License
Classifier: Operating System :: OS Independent
